mkcommit/__init__.py
mkcommit/blocks.py
mkcommit/editor_handler.py
mkcommit/fixtures.py
mkcommit/include.py
mkcommit/main.py
mkcommit/model.py
mkcommit/module_utils.py
mkcommit/validators.py
mkcommit/suites/__init__.py
mkcommit/suites/conventional.py
mkcommit/suites/semantic.py
mkcommit/suites/technica.py
test/__init__.py
test/tests/__init__.py
test/tests/test_basic.py
test/tests/test_suites.py
test/tests/test_validators.py
mkcommit-1.3.2.dist-info/LICENSE
mkcommit-1.3.2.dist-info/METADATA
mkcommit-1.3.2.dist-info/WHEEL
mkcommit-1.3.2.dist-info/entry_points.txt
mkcommit-1.3.2.dist-info/top_level.txt
mkcommit-1.3.2.dist-info/RECORD
