Metadata-Version: 2.1
Name: mkcommit
Version: 1.3.2
Summary: Dead-simple tool for enforcing clean commit messages.
Home-page: https://github.com/kjczarne/mkcommit
Author: Krzysztof J. Czarnecki
Author-email: kjczarne@gmail.com
License: MIT
Keywords: git,commit,style,templates
Platform: UNKNOWN
Classifier: License :: OSI Approved :: MIT License
Classifier: Programming Language :: Python :: 3
Classifier: Programming Language :: Python :: 3.7
Requires-Python: >=3.6
License-File: LICENSE
Requires-Dist: InquirerPy
Requires-Dist: pyperclip
Requires-Dist: prettyprinter
Requires-Dist: pyyaml
Requires-Dist: requests
Provides-Extra: dev
Requires-Dist: pdoc3 ; extra == 'dev'
Requires-Dist: flake8 ; extra == 'dev'
Requires-Dist: twine ; extra == 'dev'
Requires-Dist: setuptools ; extra == 'dev'
Requires-Dist: autopep8 ; extra == 'dev'
Requires-Dist: nox ; extra == 'dev'
